langxchange/EnhancedAgent.py
langxchange/__init__.py
langxchange/agent_memory_helper.py
langxchange/anthropic_helper.py
langxchange/chroma_helper.py
langxchange/deepseek_helper.py
langxchange/documentloader.py
langxchange/elasticsearch_helper.py
langxchange/embeddings.py
langxchange/faiss_helper.py
langxchange/gmail_tool.py
langxchange/google_cs_helper.py
langxchange/google_drive_helper.py
langxchange/google_genai_helper.py
langxchange/llama_helper.py
langxchange/localizellm.py
langxchange/localllm.py
langxchange/mcp_helper.py
langxchange/milvus_helper.py
langxchange/mongo_helper.py
langxchange/mysql_helper.py
langxchange/openai_helper.py
langxchange/pinecone_helper.py
langxchange/prompt_helper.py
langxchange/retrieverX.py
langxchange-0.4.6.dist-info/METADATA
langxchange-0.4.6.dist-info/WHEEL
langxchange-0.4.6.dist-info/top_level.txt
langxchange-0.4.6.dist-info/RECORD
