Metadata-Version: 2.4
Name: langxchange
Version: 0.4.6
Summary: AI Framework for fast integration of Private Data and LLM
Author: Timothy Owusu
Author-email: ikolilu.tim.owusu@gmail.com
Requires-Python: >=3.8
Requires-Dist: pandas
Requires-Dist: sentence-transformers
Requires-Dist: chromadb
Requires-Dist: pinecone-client
Requires-Dist: sqlalchemy
Requires-Dist: pymongo
Requires-Dist: pymysql
Requires-Dist: numpy
Requires-Dist: google-generativeai
Requires-Dist: openai
Requires-Dist: anthropic
Requires-Dist: weaviate-client
Requires-Dist: qdrant-client
Requires-Dist: elasticsearch
Requires-Dist: elasticsearch-dsl
Requires-Dist: opensearch-py
Requires-Dist: faiss-cpu
Requires-Dist: pymilvus>=2.3.0
Dynamic: author
Dynamic: author-email
Dynamic: description
Dynamic: description-content-type
Dynamic: requires-dist
Dynamic: requires-python
Dynamic: summary
